odoo/addons/fieldservice_project/README.rst
odoo/addons/fieldservice_project/__init__.py
odoo/addons/fieldservice_project/__manifest__.py
odoo/addons/fieldservice_project/i18n/de.po
odoo/addons/fieldservice_project/i18n/es.po
odoo/addons/fieldservice_project/i18n/es_AR.po
odoo/addons/fieldservice_project/i18n/es_CL.po
odoo/addons/fieldservice_project/i18n/fieldservice_project.pot
odoo/addons/fieldservice_project/i18n/fr.po
odoo/addons/fieldservice_project/i18n/it.po
odoo/addons/fieldservice_project/i18n/pl.po
odoo/addons/fieldservice_project/i18n/pt_BR.po
odoo/addons/fieldservice_project/models/__init__.py
odoo/addons/fieldservice_project/models/fsm_location.py
odoo/addons/fieldservice_project/models/fsm_order.py
odoo/addons/fieldservice_project/models/fsm_team.py
odoo/addons/fieldservice_project/models/project.py
odoo/addons/fieldservice_project/models/project_task.py
odoo/addons/fieldservice_project/readme/CONTRIBUTORS.md
odoo/addons/fieldservice_project/readme/CREDITS.md
odoo/addons/fieldservice_project/readme/DESCRIPTION.md
odoo/addons/fieldservice_project/readme/ROADMAP.md
odoo/addons/fieldservice_project/readme/USAGE.md
odoo/addons/fieldservice_project/security/ir.model.access.csv
odoo/addons/fieldservice_project/static/description/icon.png
odoo/addons/fieldservice_project/static/description/icon.svg
odoo/addons/fieldservice_project/static/description/index.html
odoo/addons/fieldservice_project/static/src/scss/project_column.scss
odoo/addons/fieldservice_project/tests/__init__.py
odoo/addons/fieldservice_project/tests/common.py
odoo/addons/fieldservice_project/tests/test_fsm_location.py
odoo/addons/fieldservice_project/tests/test_fsm_order.py
odoo/addons/fieldservice_project/tests/test_project.py
odoo/addons/fieldservice_project/tests/test_project_task.py
odoo/addons/fieldservice_project/views/fsm_location_views.xml
odoo/addons/fieldservice_project/views/fsm_order_views.xml
odoo/addons/fieldservice_project/views/fsm_team.xml
odoo_addon_fieldservice_project-18.0.1.0.0.4.dist-info/METADATA
odoo_addon_fieldservice_project-18.0.1.0.0.4.dist-info/WHEEL
odoo_addon_fieldservice_project-18.0.1.0.0.4.dist-info/top_level.txt
odoo_addon_fieldservice_project-18.0.1.0.0.4.dist-info/RECORD
